[{"batches": [{"train_loss": 1.6639690399169922, "train_batch_size": 16}, {"train_loss": 1.6510285139083862, "train_batch_size": 16}, {"train_loss": 1.5722191333770752, "train_batch_size": 16}, {"train_loss": 1.5694541931152344, "train_batch_size": 16}, {"train_loss": 1.5331109762191772, "train_batch_size": 16}, {"train_loss": 1.561470627784729, "train_batch_size": 16}, {"train_loss": 1.5444453954696655, "train_batch_size": 16}, {"train_loss": 1.496492862701416, "train_batch_size": 16}, {"train_loss": 1.4788423776626587, "train_batch_size": 16}, {"train_loss": 1.5198057889938354, "train_batch_size": 16}, {"train_loss": 1.4741822481155396, "train_batch_size": 16}, {"train_loss": 1.4435651302337646, "train_batch_size": 16}, {"train_loss": 1.401024580001831, "train_batch_size": 16}, {"train_loss": 1.4136149883270264, "train_batch_size": 16}, {"train_loss": 1.3521016836166382, "train_batch_size": 16}, {"train_loss": 1.484174370765686, "train_batch_size": 16}, {"train_loss": 1.360398292541504, "train_batch_size": 16}, {"train_loss": 1.3490475416183472, "train_batch_size": 16}, {"train_loss": 1.3049471378326416, "train_batch_size": 16}, {"train_loss": 1.2823002338409424, "train_batch_size": 16}, {"train_loss": 1.3077605962753296, "train_batch_size": 16}, {"train_loss": 1.235906720161438, "train_batch_size": 16}, {"train_loss": 1.2857249975204468, "train_batch_size": 16}, {"train_loss": 1.3105863332748413, "train_batch_size": 16}, {"train_loss": 1.2292176485061646, "train_batch_size": 16}, {"train_loss": 1.2912054061889648, "train_batch_size": 16}, {"train_loss": 1.1514896154403687, "train_batch_size": 16}, {"train_loss": 1.169835090637207, "train_batch_size": 16}, {"train_loss": 1.2224704027175903, "train_batch_size": 16}, {"train_loss": 1.119580626487732, "train_batch_size": 16}, {"train_loss": 1.2020227909088135, "train_batch_size": 16}, {"train_loss": 1.1860225200653076, "train_batch_size": 16}, {"train_loss": 1.1821370124816895, "train_batch_size": 8}, {"valid_loss": 0.5010780096054077, "valid_batch_size": 16}, {"valid_loss": 0.48805001378059387, "valid_batch_size": 16}, {"valid_loss": 0.5290407538414001, "valid_batch_size": 16}, {"valid_loss": 0.462283730506897, "valid_batch_size": 16}, {"valid_loss": 0.5244489312171936, "valid_batch_size": 16}, {"valid_loss": 0.4768119752407074, "valid_batch_size": 16}, {"valid_loss": 0.4811919629573822, "valid_batch_size": 16}, {"valid_loss": 0.5252682566642761, "valid_batch_size": 16}, {"valid_loss": 0.3844897150993347, "valid_batch_size": 2}], "epoch": 1, "train_batch_count": 33, "valid_batch_count": 9, "dur": 172.2302281856537, "train_loss": 1.3772026575528657, "train_loss_best": true, "valid_loss": 0.4967673659324646, "valid_loss_best": true, "event_cp": true}]